grid_run/__init__.py
grid_run/runner.py
grid_run-0.2.dist-info/LICENSE
grid_run-0.2.dist-info/METADATA
grid_run-0.2.dist-info/WHEEL
grid_run-0.2.dist-info/top_level.txt
grid_run-0.2.dist-info/RECORD
