Metadata-Version: 2.1
Name: grid-run
Version: 0.2
Summary: A simple tool for executing and managing shell commands
Author-email: Ruixiang JIANG <1138561926@qq.com>
License: MIT License        
Project-URL: Homepage, https://github.com/songrise/GridRun
Project-URL: Bug Tracker, https://github.com/songrise/GridRun/issues
Classifier: Programming Language :: Python :: 3
Classifier: License :: OSI Approved :: MIT License
Classifier: Operating System :: OS Independent
Requires-Python: >=3.7
License-File: LICENSE
